hamlish/__init__.py
hamlish/__main__.py
hamlish/converter.py
hamlish/docnode.py
hamlish/exception.py
hamlish/extension.py
hamlish/parser.py
hamlish/py.typed
Hamlish-0.4.0.dist-info/AUTHORS
Hamlish-0.4.0.dist-info/LICENSE
Hamlish-0.4.0.dist-info/METADATA
Hamlish-0.4.0.dist-info/WHEEL
Hamlish-0.4.0.dist-info/entry_points.txt
Hamlish-0.4.0.dist-info/top_level.txt
Hamlish-0.4.0.dist-info/RECORD
